{
  "uid": "wm-business",
  "title": "Watermelon — Бизнес",
  "tags": ["watermelon", "business"],
  "timezone": "browser",
  "schemaVersion": 39,
  "version": 1,
  "refresh": "30s",
  "time": { "from": "now-24h", "to": "now" },
  "panels": [
    {
      "type": "stat",
      "title": "Пользователи",
      "gridPos": { "h": 4, "w": 4, "x": 0, "y": 0 },
      "targets": [{ "expr": "wm_users_total", "refId": "A" }],
      "options": { "reduceOptions": { "calcs": ["lastNotNull"] }, "colorMode": "value" },
      "fieldConfig": { "defaults": { "unit": "short" } }
    },
    {
      "type": "stat",
      "title": "Ожидают beta",
      "gridPos": { "h": 4, "w": 4, "x": 4, "y": 0 },
      "targets": [{ "expr": "wm_beta_pending_users", "refId": "A" }],
      "options": { "reduceOptions": { "calcs": ["lastNotNull"] } },
      "fieldConfig": { "defaults": { "unit": "short", "color": { "mode": "thresholds" }, "thresholds": { "steps": [{ "color": "green", "value": null }, { "color": "orange", "value": 1 }] } } }
    },
    {
      "type": "stat",
      "title": "Чаты",
      "gridPos": { "h": 4, "w": 4, "x": 8, "y": 0 },
      "targets": [{ "expr": "wm_chats_total", "refId": "A" }],
      "options": { "reduceOptions": { "calcs": ["lastNotNull"] } }
    },
    {
      "type": "stat",
      "title": "Группы",
      "gridPos": { "h": 4, "w": 4, "x": 12, "y": 0 },
      "targets": [{ "expr": "wm_group_chats_total", "refId": "A" }],
      "options": { "reduceOptions": { "calcs": ["lastNotNull"] } }
    },
    {
      "type": "stat",
      "title": "Platinum",
      "gridPos": { "h": 4, "w": 4, "x": 16, "y": 0 },
      "targets": [{ "expr": "wm_platinum_users_total", "refId": "A" }],
      "options": { "reduceOptions": { "calcs": ["lastNotNull"] } }
    },
    {
      "type": "stat",
      "title": "Push-подписки",
      "gridPos": { "h": 4, "w": 4, "x": 20, "y": 0 },
      "targets": [{ "expr": "wm_push_subscriptions_total", "refId": "A" }],
      "options": { "reduceOptions": { "calcs": ["lastNotNull"] } }
    },
    {
      "type": "timeseries",
      "title": "Сообщения в минуту",
      "gridPos": { "h": 8, "w": 12, "x": 0, "y": 4 },
      "targets": [{ "expr": "rate(wm_messages_total[5m]) * 60", "legendFormat": "сообщений/мин", "refId": "A" }],
      "fieldConfig": { "defaults": { "unit": "short", "custom": { "drawStyle": "line", "fillOpacity": 20 } } }
    },
    {
      "type": "timeseries",
      "title": "WebSocket онлайн",
      "gridPos": { "h": 8, "w": 12, "x": 12, "y": 4 },
      "targets": [
        { "expr": "wm_ws_connections", "legendFormat": "соединения", "refId": "A" },
        { "expr": "wm_ws_users_online", "legendFormat": "пользователи", "refId": "B" }
      ],
      "fieldConfig": { "defaults": { "unit": "short", "custom": { "drawStyle": "line", "fillOpacity": 15 } } }
    },
    {
      "type": "timeseries",
      "title": "Всего сообщений (накопительно)",
      "gridPos": { "h": 8, "w": 24, "x": 0, "y": 12 },
      "targets": [{ "expr": "wm_messages_total", "legendFormat": "messages", "refId": "A" }],
      "fieldConfig": { "defaults": { "unit": "short", "custom": { "drawStyle": "line", "fillOpacity": 10 } } }
    }
  ]
}
